setup.cfg
setup.py
tgext/__init__.py
tgext.coffeescript.egg-info/PKG-INFO
tgext.coffeescript.egg-info/SOURCES.txt
tgext.coffeescript.egg-info/dependency_links.txt
tgext.coffeescript.egg-info/entry_points.txt
tgext.coffeescript.egg-info/namespace_packages.txt
tgext.coffeescript.egg-info/not-zip-safe
tgext.coffeescript.egg-info/requires.txt
tgext.coffeescript.egg-info/top_level.txt
tgext/coffeescript/__init__.py
tgext/coffeescript/jinja.py
tgext/coffeescript/middleware.py