Metadata-Version: 1.0
Name: tgext.coffeescript
Version: 0.3.1
Summary: CoffeeScript middleware for TurboGears2
Home-page: http://bitbucket.org/clsdaniel/tgext.coffeescript
Author: Carlos Daniel Ruvalcaba Valenzuela
Author-email: clsdaniel@gmail.com
License: MIT
Keywords: turbogears2.extension CoffeeScript WSGI jinja2.extension
Platform: UNKNOWN
Classifier: Environment :: Web Environment
Classifier: Topic :: Software Development :: Libraries :: Python Modules
Classifier: License :: OSI Approved :: MIT License
Classifier: Framework :: TurboGears
